vdms/__init__.py
vdms/queryMessage_pb2.py
vdms/vdms.py
vdms-0.0.22.dist-info/METADATA
vdms-0.0.22.dist-info/WHEEL
vdms-0.0.22.dist-info/top_level.txt
vdms-0.0.22.dist-info/RECORD
