Metadata-Version: 2.4
Name: vdms
Version: 0.0.22
Summary: VDMS Client Module
Home-page: https://github.com/IntelLabs/vdms
Author: Chaunté W. Lacewell
Author-email: chaunte.w.lacewell@intel.com
License: MIT
Classifier: Programming Language :: Python :: 3
Classifier: License :: OSI Approved :: MIT License
Classifier: Operating System :: OS Independent
Requires-Python: >=2.6, !=3.0.*, !=3.1.*, !=3.2.*, <4
Requires-Dist: protobuf==5.29.5
Dynamic: author
Dynamic: author-email
Dynamic: classifier
Dynamic: description
Dynamic: description-content-type
Dynamic: home-page
Dynamic: license
Dynamic: requires-dist
Dynamic: requires-python
Dynamic: summary
